gradio/CHANGELOG.md
gradio/__init__.py
gradio/package.json
gradio/util.py
gradio/version.txt
gradio_test_pypi-0.51.8.dist-info/METADATA
gradio_test_pypi-0.51.8.dist-info/WHEEL
gradio_test_pypi-0.51.8.dist-info/entry_points.txt
gradio_test_pypi-0.51.8.dist-info/RECORD
