Metadata-Version: 2.4
Name: gradio-test-pypi
Version: 0.51.8
Summary: Python library for easily interacting with trained machine learning models
Project-URL: Homepage, https://github.com/gradio-app/gradio
Author-email: Abubakar Abid <team@gradio.app>, Ali Abid <team@gradio.app>, Ali Abdalla <team@gradio.app>, Dawood Khan <team@gradio.app>, Ahsen Khaliq <team@gradio.app>, Pete Allen <team@gradio.app>, Ömer Faruk Özdemir <team@gradio.app>
License-Expression: Apache-2.0
Keywords: machine learning,reproducibility,visualization
Classifier: Development Status :: 5 - Production/Stable
Classifier: License :: OSI Approved :: Apache Software License
Classifier: Operating System :: OS Independent
Classifier: Programming Language :: Python :: 3
Classifier: Programming Language :: Python :: 3 :: Only
Classifier: Programming Language :: Python :: 3.8
Classifier: Programming Language :: Python :: 3.9
Classifier: Programming Language :: Python :: 3.10
Classifier: Programming Language :: Python :: 3.11
Classifier: Topic :: Scientific/Engineering
Classifier: Topic :: Scientific/Engineering :: Artificial Intelligence
Classifier: Topic :: Scientific/Engineering :: Visualization
Requires-Python: >=3.8
Requires-Dist: aiofiles
Requires-Dist: aiohttp
Requires-Dist: altair>=4.2.0
Requires-Dist: fastapi
Requires-Dist: ffmpy
Requires-Dist: gradio-test-client-pypi>=48.1.0
Requires-Dist: httpx
Requires-Dist: huggingface-hub>=0.14.0
Requires-Dist: jinja2
Requires-Dist: markdown-it-py[linkify]>=2.0.0
Requires-Dist: markupsafe
Requires-Dist: matplotlib
Requires-Dist: mdit-py-plugins<=0.3.3
Requires-Dist: numpy
Requires-Dist: orjson
Requires-Dist: pandas
Requires-Dist: pillow
Requires-Dist: pydantic
Requires-Dist: pydub
Requires-Dist: pygments>=2.12.0
Requires-Dist: python-multipart
Requires-Dist: pyyaml
Requires-Dist: requests
Requires-Dist: semantic-version
Requires-Dist: uvicorn>=0.14.0
Requires-Dist: websockets>=10.0
